walt/__init__.py
walt/server/__init__.py
walt/server/annotatecmd.py
walt/server/autoglob.py
walt/server/config.py
walt/server/const.py
walt/server/daemon.py
walt/server/dhcpevent.py
walt/server/diskcache.py
walt/server/exttools.py
walt/server/imagecheck.py
walt/server/netconfig.py
walt/server/popen.py
walt/server/process.py
walt/server/regex.py
walt/server/spec.py
walt/server/tools.py
walt/server/ext/__init__.py
walt/server/ext/_c_ext.abi3.so
walt/server/ext/build.py
walt/server/ext/posix_regex.c
walt/server/ext/vpn.c
walt/server/mount/__init__.py
walt/server/mount/mount.py
walt/server/mount/setup.py
walt/server/mount/tools.py
walt/server/mount/umount.py
walt/server/mount/walt-boot-modes
walt/server/mount/walt-cat
walt/server/mount/walt-clock-sync
walt/server/mount/walt-dump-diff-tar
walt/server/mount/walt-echo
walt/server/mount/walt-env
walt/server/mount/walt-fs-watchdog
walt/server/mount/walt-init
walt/server/mount/walt-init-finalfs
walt/server/mount/walt-init-nbd
walt/server/mount/walt-init-rootfs
walt/server/mount/walt-init-rootfs-main
walt/server/mount/walt-log-cat
walt/server/mount/walt-log-echo
walt/server/mount/walt-log-script
walt/server/mount/walt-log-tee
walt/server/mount/walt-net-service
walt/server/mount/walt-net-service-handler
walt/server/mount/walt-notify-bootup
walt/server/mount/walt-report-lldp-neighbor
walt/server/mount/walt-rpc
walt/server/mount/walt-script-common
walt/server/mount/walt-tar-send
walt/server/mount/walt-tee
walt/server/mount/walt-timeout
walt/server/processes/__init__.py
walt/server/processes/blocking/__init__.py
walt/server/processes/blocking/cmd.py
walt/server/processes/blocking/process.py
walt/server/processes/blocking/registries.py
walt/server/processes/blocking/service.py
walt/server/processes/blocking/devices/__init__.py
walt/server/processes/blocking/devices/grouper.py
walt/server/processes/blocking/devices/loops.py
walt/server/processes/blocking/devices/topology.py
walt/server/processes/blocking/devices/tree.py
walt_server-10.0.dist-info/METADATA
walt_server-10.0.dist-info/WHEEL
walt_server-10.0.dist-info/entry_points.txt
walt_server-10.0.dist-info/top_level.txt
walt_server-10.0.dist-info/RECORD
