Metadata-Version: 2.4
Name: walt-server
Version: 10.0
Summary: WalT server components.
Home-page: https://walt-project.liglab.fr
Author: WalT developers
Author-email: walt-contact@univ-grenoble-alpes.fr
License: 3-Clause BSD
Keywords: WalT testbed
Requires-Dist: aiohappyeyeballs==2.3.7
Requires-Dist: aiohttp==3.10.11
Requires-Dist: aiosignal==1.3.1
Requires-Dist: aiostream==0.5.2
Requires-Dist: attrs==23.2.0
Requires-Dist: bottle==0.12.25
Requires-Dist: certifi==2024.7.4
Requires-Dist: cffi==1.16.0
Requires-Dist: charset-normalizer==3.3.2
Requires-Dist: commonmark==0.9.1
Requires-Dist: cryptography==44.0.2
Requires-Dist: dnspython==2.7.0
Requires-Dist: frozenlist==1.4.1
Requires-Dist: gevent==24.2.1
Requires-Dist: greenlet==3.0.3
Requires-Dist: idna==3.7
Requires-Dist: ipaddress==1.0.23
Requires-Dist: jinja2==3.1.6
Requires-Dist: llvmlite==0.42.0
Requires-Dist: markupsafe==2.1.5
Requires-Dist: multidict==6.0.5
Requires-Dist: netifaces==0.11.0
Requires-Dist: numba==0.59.1
Requires-Dist: numpy==1.26.4
Requires-Dist: plumbum==1.8.2
Requires-Dist: ply==3.11
Requires-Dist: podman==5.0.0
Requires-Dist: propcache==0.2.0
Requires-Dist: psycopg2-binary==2.9.9
Requires-Dist: pyasn1==0.6.0
Requires-Dist: pycparser==2.22
Requires-Dist: pygments==2.17.2
Requires-Dist: pysmi-lextudio==1.4.3
Requires-Dist: pysnmp-lextudio==5.0.34
Requires-Dist: pysnmpcrypto==0.0.4
Requires-Dist: python-apt-binary
Requires-Dist: python-dateutil==2.9.0.post0
Requires-Dist: pyxdg==0.28
Requires-Dist: pyyaml==6.0.1
Requires-Dist: requests==2.32.4
Requires-Dist: sdnotify==0.3.2
Requires-Dist: setproctitle==1.3.3
Requires-Dist: setuptools==78.1.1
Requires-Dist: six==1.16.0
Requires-Dist: snimpy==1.0.3
Requires-Dist: typing-extensions==4.11.0
Requires-Dist: urllib3==2.5.0
Requires-Dist: walt-client==10.0
Requires-Dist: walt-common==10.0
Requires-Dist: walt-doc==10.0
Requires-Dist: walt-virtual==10.0
Requires-Dist: yarl==1.17.2
Requires-Dist: zope.event==5.0
Requires-Dist: zope.interface==6.3
Dynamic: author
Dynamic: author-email
Dynamic: home-page
Dynamic: keywords
Dynamic: license
Dynamic: requires-dist
Dynamic: summary
